{"lastUsed":1649063277407,"path":"C:\/Users\/1004s\/OneDrive\/Desktop\/Repository\/Eclipse","projectCount":16,"recentFiles":[{"path":"\/9020\/src","parentWorkspace":"C:\/Users\/1004s\/OneDrive\/Desktop\/Repository\/Eclipse","name":"Main.java","lastModified":1648692538384,"locationURI":"file:\/C:\/Users\/1004s\/OneDrive\/Desktop\/Repository\/Eclipse\/9020\/src\/Main.java"},{"path":"\/8087\/src","parentWorkspace":"C:\/Users\/1004s\/OneDrive\/Desktop\/Repository\/Eclipse","name":"prac8087.java","lastModified":1648894392589,"locationURI":"file:\/C:\/Users\/1004s\/OneDrive\/Desktop\/Repository\/Eclipse\/8087\/src\/prac8087.java"},{"path":"\/9010\/src","parentWorkspace":"C:\/Users\/1004s\/OneDrive\/Desktop\/Repository\/Eclipse","name":"Main.java","lastModified":1648691366978,"locationURI":"file:\/C:\/Users\/1004s\/OneDrive\/Desktop\/Repository\/Eclipse\/9010\/src\/Main.java"},{"path":"\/8020\/src","parentWorkspace":"C:\/Users\/1004s\/OneDrive\/Desktop\/Repository\/Eclipse","name":"Main.java","lastModified":1648652593887,"locationURI":"file:\/C:\/Users\/1004s\/OneDrive\/Desktop\/Repository\/Eclipse\/8020\/src\/Main.java"},{"path":"\/test\/src\/test","parentWorkspace":"C:\/Users\/1004s\/OneDrive\/Desktop\/Repository\/Eclipse","name":"test.java","lastModified":1648869369894,"locationURI":"file:\/C:\/Users\/1004s\/OneDrive\/Desktop\/Repository\/Eclipse\/test\/src\/test\/test.java"},{"path":"\/8082\/src","parentWorkspace":"C:\/Users\/1004s\/OneDrive\/Desktop\/Repository\/Eclipse","name":"Main.java","lastModified":1648509156371,"locationURI":"file:\/C:\/Users\/1004s\/OneDrive\/Desktop\/Repository\/Eclipse\/8082\/src\/Main.java"},{"path":"\/8083\/src","parentWorkspace":"C:\/Users\/1004s\/OneDrive\/Desktop\/Repository\/Eclipse","name":"prac8083.java","lastModified":1648515758214,"locationURI":"file:\/C:\/Users\/1004s\/OneDrive\/Desktop\/Repository\/Eclipse\/8083\/src\/prac8083.java"},{"path":"\/8070\/src","parentWorkspace":"C:\/Users\/1004s\/OneDrive\/Desktop\/Repository\/Eclipse","name":"Main.java","lastModified":1648653374892,"locationURI":"file:\/C:\/Users\/1004s\/OneDrive\/Desktop\/Repository\/Eclipse\/8070\/src\/Main.java"},{"path":"\/8072\/src","parentWorkspace":"C:\/Users\/1004s\/OneDrive\/Desktop\/Repository\/Eclipse","name":"Queue.java","lastModified":1648667022253,"locationURI":"file:\/C:\/Users\/1004s\/OneDrive\/Desktop\/Repository\/Eclipse\/8072\/src\/Queue.java"},{"path":"\/8072\/src","parentWorkspace":"C:\/Users\/1004s\/OneDrive\/Desktop\/Repository\/Eclipse","name":"Main.java","lastModified":1648667064427,"locationURI":"file:\/C:\/Users\/1004s\/OneDrive\/Desktop\/Repository\/Eclipse\/8072\/src\/Main.java"},{"path":"\/9050\/src","parentWorkspace":"C:\/Users\/1004s\/OneDrive\/Desktop\/Repository\/Eclipse","name":"Main.java","lastModified":1648693487937,"locationURI":"file:\/C:\/Users\/1004s\/OneDrive\/Desktop\/Repository\/Eclipse\/9050\/src\/Main.java"},{"path":"\/8010\/src","parentWorkspace":"C:\/Users\/1004s\/OneDrive\/Desktop\/Repository\/Eclipse","name":"Main.java","lastModified":1648518303282,"locationURI":"file:\/C:\/Users\/1004s\/OneDrive\/Desktop\/Repository\/Eclipse\/8010\/src\/Main.java"},{"path":"\/8082\/src","parentWorkspace":"C:\/Users\/1004s\/OneDrive\/Desktop\/Repository\/Eclipse","name":"MyScanner.java","lastModified":1648518443125,"locationURI":"file:\/C:\/Users\/1004s\/OneDrive\/Desktop\/Repository\/Eclipse\/8082\/src\/MyScanner.java"},{"path":"\/8070\/src","parentWorkspace":"C:\/Users\/1004s\/OneDrive\/Desktop\/Repository\/Eclipse","name":"Person.java","lastModified":1648653655921,"locationURI":"file:\/C:\/Users\/1004s\/OneDrive\/Desktop\/Repository\/Eclipse\/8070\/src\/Person.java"},{"path":"\/9010\/src","parentWorkspace":"C:\/Users\/1004s\/OneDrive\/Desktop\/Repository\/Eclipse","name":"Dog.java","lastModified":1648691221132,"locationURI":"file:\/C:\/Users\/1004s\/OneDrive\/Desktop\/Repository\/Eclipse\/9010\/src\/Dog.java"},{"path":"\/ExceptionPrac\/src","parentWorkspace":"C:\/Users\/1004s\/OneDrive\/Desktop\/Repository\/Eclipse","name":"ExceptionPrac.java","lastModified":1648651359717,"locationURI":"file:\/C:\/Users\/1004s\/OneDrive\/Desktop\/Repository\/Eclipse\/ExceptionPrac\/src\/ExceptionPrac.java"},{"path":"\/8071\/src","parentWorkspace":"C:\/Users\/1004s\/OneDrive\/Desktop\/Repository\/Eclipse","name":"Stack.java","lastModified":1648665809293,"locationURI":"file:\/C:\/Users\/1004s\/OneDrive\/Desktop\/Repository\/Eclipse\/8071\/src\/Stack.java"},{"path":"\/8071\/src","parentWorkspace":"C:\/Users\/1004s\/OneDrive\/Desktop\/Repository\/Eclipse","name":"Main.java","lastModified":1648665307192,"locationURI":"file:\/C:\/Users\/1004s\/OneDrive\/Desktop\/Repository\/Eclipse\/8071\/src\/Main.java"}]}